timeoutthreadpoolexecutor.py
timeoutthreadpoolexecutor-1.0.2.dist-info/METADATA
timeoutthreadpoolexecutor-1.0.2.dist-info/WHEEL
timeoutthreadpoolexecutor-1.0.2.dist-info/top_level.txt
timeoutthreadpoolexecutor-1.0.2.dist-info/RECORD
