Metadata-Version: 2.1
Name: timeoutthreadpoolexecutor
Version: 1.0.2
Summary: A backported ThreadPoolExecutor with thread TTL
Home-page: https://github.com/JohnDoee/timeoutthreadpoolexecutor
Author: Anders Jensen
Author-email: andersandjensen@gmail.com
License: MIT
Platform: UNKNOWN
Classifier: Development Status :: 4 - Beta
Classifier: Environment :: Web Environment
Classifier: Intended Audience :: Developers
Classifier: License :: OSI Approved :: Python Software Foundation License
Classifier: Operating System :: OS Independent
Classifier: Programming Language :: Python
Classifier: Programming Language :: Python :: 3
Classifier: Programming Language :: Python :: 3.7
Classifier: Programming Language :: Python :: 3.8
Classifier: Topic :: Software Development :: Libraries :: Python Modules
